{
  "brandColors": {
    "brand": {
      "value": "{colors.brandColors.7mind}",
      "type": "color"
    },
    "light": {
      "1": {
        "value": "{colors.light blue.200}",
        "type": "color"
      },
      "2": {
        "value": "{colors.light blue.500}",
        "type": "color"
      },
      "3": {
        "value": "{colors.light blue.100}",
        "type": "color"
      },
      "4": {
        "value": "{colors.beige.100}",
        "type": "color"
      },
      "5": {
        "value": "rgba(21,73,62, 0.2)",
        "type": "color",
        "description": "Semi transparent light1"
      }
    },
    "dark": {
      "1": {
        "value": "{colors.teal.900}",
        "type": "color"
      },
      "2": {
        "value": "{colors.blue.700}",
        "type": "color"
      },
      "3": {
        "value": "{colors.teal.1000}",
        "type": "color"
      },
      "4": {
        "value": "{colors.teal.900}",
        "type": "color"
      },
      "5": {
        "value": "rgba(204,231,239, 0.2)",
        "type": "color",
        "description": "Semi transparent dark1"
      }
    }
  }
}